 [
    {
        "diameter": 40.0,
        "MF Flange": "MF Flange 150",
        "DC Clamp Assembly": "[VAC-035] DC CLAMP ASSY_CENTERING_80A_MF",
        "Reducer": "Reducer 150",
        "KF Flange": "[VAC-058] KF FLANGE_SUS_40A",
        "NRC Clamp": "[VAC-087] NRC CLAMP ASSY_40_KF",
        "Dual Bellows": "[VAC-101] DUAL BELLOWS TI_SUS_NW40_150L",
        "Centering": "[VAC-025] CENTERING_NW80",
        "Super Bellows": "[VAC-138] BELLOWS SUPPORT_NW100_200L(6ea Clamp)",
        "Middle Foreline": "Middle Foreline 150",
        "Pipe": "Test_pipe",
        "Reducer_40_100": "Reducer_40_100",
        "Reducer_100_125":"Reducer_100_125"
    },
    {
        "diameter": 50.0,
        "MF Flange": "MF Flange 150",
        "DC Clamp Assembly": "[VAC-035] DC CLAMP ASSY_CENTERING_80A_MF",
        "Reducer": "Reducer 150",
        "KF Flange": "[VAC-059] KF FLANGE_SUS_50A",
        "NRC Clamp": "[VAC-088] NRC CLAMP ASSY_50_KF",
        "Dual Bellows": "[VAC-133] DUAL BELLOWS TI_SUS_NW50_150L",
        "Centering": "[VAC-025] CENTERING_NW80",
        "Super Bellows": "[VAC-138] BELLOWS SUPPORT_NW100_200L(6ea Clamp)",
        "Middle Foreline": "Middle Foreline 150",
        "Pipe": "Test_pipe",
        "Reducer_50_100": "Reducer_50_100",
        "Reducer_100_125":"Reducer_100_125"
    },
    {
        "diameter": 80.0,
        "MF Flange": "[VAC-072] MF FLANGE_NW80",
        "DC Clamp Assembly": "[VAC-035] DC CLAMP ASSY_CENTERING_80A_MF",
        "Reducer": "Reducer 150",
        "KF Flange": "KF Flange 150",
        "NRC Clamp": "NRC Clamp 150",
        "Dual Bellows": "[VAC-065] MF BELLOWS_NW80_200L",
        "Centering": "[VAC-025] CENTERING_NW80",
        "Super Bellows": "[VAC-065] MF BELLOWS_NW80_200L",
        "Middle Foreline": "Middle Foreline 150",
        "Pipe": "Test_pipe",
        "Reducer_80_125": "Reducer_80_125"
    },
    {
        "diameter": 100.0,
        "MF Flange": "[VAC-073] MF FLANGE_NW100",
        "DC Clamp Assembly": "[VAC-136] 6EA DC CLAMP ASSY_CENTERING_100A_MF",
        "Reducer": "Reducer 150",
        "KF Flange": "[VAC-059] KF FLANGE_SUS_50A",
        "NRC Clamp": "[VAC-088] NRC CLAMP ASSY_50_KF",
        "Dual Bellows": "[VAC-133] DUAL BELLOWS TI_SUS_NW50_150L",
        "Centering": "[VAC-026] CENTERING_NW100",
        "Super Bellows": "[VAC-066] MF BELLOWS_SUS_NW100_200L",
        "Middle Foreline": "[VAC-078] MIDDLE FORELINE_100A_1000L",
        "Pipe": "Test_pipe",
        "Reducer_100_125":"Reducer_100_125"
    },
    {
        "diameter": 125.0,
        "MF Flange": "[VAC-074] MF FLANGE_NW125",
        "DC Clamp Assembly": "[VAC-037] DC CLAMP ASSY_CENTERING_125A_MF",
        "Reducer": "Reducer 200",
        "KF Flange": "KF Flange 200",
        "NRC Clamp": "NRC Clamp 200",
        "Dual Bellows": "Dual Bellows 200",
        "Centering": "[VAC-027] CENTERING_NW125",
        "Super Bellows": "[VAC-008] BELLOWS SUPPORT_NW125_200L",
        "Middle Foreline": "[VAC-079] MIDDLE FORELINE_125A_1000L",
        "Pipe": "Test_pipe"
    },
    {
        "diameter": 160.0,
        "MF Flange": "[VAC-075] MF FLANGE_NW160",
        "DC Clamp Assembly": "[VAC-038] DC CLAMP ASSY_CENTERING_160A_MF",
        "Reducer": "Reducer 250",
        "KF Flange": "KF Flange 250",
        "NRC Clamp": "NRC Clamp 250",
        "Dual Bellows": "Dual Bellows 250",
        "Centering": "[VAC-028] CENTERING_NW160",
        "Super Bellows": "[VAC-009] BELLOWS SUPPORT_NW160_200L",
        "Middle Foreline": "[VAC-080] MIDDLE FORELINE_160A_1000L",
        "Pipe": "Test_pipe"
    },
    {
        "diameter": 200.0,
        "MF Flange": "[VAC-076] MF FLANGE_NW200",
        "DC Clamp Assembly": "[VAC-039] DC CLAMP ASSY_CENTERING_200A_MF(12N)",
        "Reducer": "Reducer 250",
        "KF Flange": "KF Flange 250",
        "NRC Clamp": "NRC Clamp 250",
        "Dual Bellows": "Dual Bellows 250",
        "Centering": "[VAC-029] CENTERING_NW200",
        "Super Bellows": "[VAC-010] BELLOWS SUPPORT_NW200_200L",
        "Middle Foreline": "[VAC-084] MIDDLE FORELINE_200A_1000L",
        "Pipe": "Test_pipe"
    }
]